PythonToSW/__init__.py
PythonToSW/addon.py
PythonToSW/enums.py
PythonToSW/exceptions.py
PythonToSW/log.py
PythonToSW/models.py
PythonToSW/addon/playlist.xml
PythonToSW/addon/script.lua
PythonToSW/libs/__init__.py
PythonToSW/libs/event.py
PythonToSW/libs/http.py
PythonToSW/libs/io.py
PythonToSW/libs/persistence.py
PythonToSW/libs/xml.py
PythonToSW/values/__init__.py
PythonToSW/values/base.py
PythonToSW/values/matrix.py
pythontosw-2.0.3.dist-info/licenses/LICENSE
pythontosw-2.0.3.dist-info/METADATA
pythontosw-2.0.3.dist-info/WHEEL
pythontosw-2.0.3.dist-info/top_level.txt
pythontosw-2.0.3.dist-info/RECORD
