Metadata-Version: 2.4
Name: PythonToSW
Version: 2.0.3
Summary: A package that allows you to create addons in Stormworks with Python, handled through HTTP.
Home-page: https://github.com/Cuh4/PythonToSW
Author: Cuh4
License: Apache License 2.0
Requires-Python: >=3.10
License-File: LICENSE
Requires-Dist: click==8.1.7
Requires-Dist: coloredlogs==15.0.1
Requires-Dist: fastapi==0.120.0
Requires-Dist: pydantic==2.12.3
Requires-Dist: pytest==8.3.4
Requires-Dist: rich==14.2.0
Requires-Dist: uvicorn==0.38.0
Requires-Dist: xmltodict==0.14.2
Dynamic: license-file
